SearchFile/Search_file.py
SearchFile/__init__.py
SearchFile-1.0.0.dist-info/LICENSE.txt
SearchFile-1.0.0.dist-info/METADATA
SearchFile-1.0.0.dist-info/WHEEL
SearchFile-1.0.0.dist-info/top_level.txt
SearchFile-1.0.0.dist-info/RECORD
