Metadata-Version: 2.1
Name: SearchFile
Version: 1.0.0
Summary: Search for files by the specified path.
Home-page: https://github.com/Artemik1/SearchFile-package
Author: Prudnikov Artem
Author-email: artem_prudnikov_2002@mail.ru
License: UNKNOWN
Platform: UNKNOWN
Classifier: Programming Language :: Python :: 3.9
Classifier: License :: OSI Approved :: MIT License
Classifier: Operating System :: OS Independent
Requires-Python: >=3.9
